{
  "meta": {
    "fecha_actual": "20/05/2026",
    "fecha_anterior": "19/05/2026",
    "duration_dias": 15.0,
    "participes": 3
  },
  "patrimonial": {
    "activo_total": 39407725873.21,
    "activo_total_prev": 39113414404.71,
    "pasivo_total": -342529841.72,
    "pasivo_total_prev": -271861615.7,
    "patrimonio_neto": 39065196031.49,
    "patrimonio_neto_prev": 38841552789.01,
    "creditos_totales": 2272364567.77,
    "creditos_totales_prev": 2256814693.66,
    "liquidez_corriente": 115.0,
    "liquidez_efectiva": 1988702740.03
  },
  "balance_detalle": {
    "provisiones": -56895985.76,
    "prov_depositaria": -3301424.94,
    "prov_gerente": -48722328.01,
    "prov_gastos": -4872232.81,
    "rescates": -69651352.05,
    "prevision_incobrables": -180014873.18,
    "deudas_pesos": -276062035.04
  },
  "cartera": {
    "cpd_pesos": 31744239317,
    "cpd_pesos_prev": 31725324158,
    "cpd_usd": 1328239833.48,
    "cpd_usd_prev": 1187937031.41,
    "pases_cauciones": 1589280416.91,
    "pases_cauciones_prev": 588678287.12,
    "money_market": 1680000000.0,
    "money_market_prev": 2364000000.0,
    "titulos_publicos": 490719364.27,
    "titulos_publicos_prev": 490921006.4,
    "obligaciones_neg": 627863748.0,
    "obligaciones_neg_prev": 627419871.0,
    "fideicomisos": 978662545.05,
    "fideicomisos_prev": 979042900.6,
    "titulo_provincial": 306461808.0,
    "titulo_provincial_prev": 307758267.0,
    "tp_det": [
      {
        "nombre": "Lecap S30N6",
        "total": 230752808.0,
        "total_prev": 231110068.0,
        "cierre": 1.1538,
        "cantidad": 200000000.0
      },
      {
        "nombre": "S29Y6 - Lecap S29Y6",
        "total": 259966556.27,
        "total_prev": 259810938.4,
        "cierre": 1.3135,
        "cantidad": 197919126.0
      }
    ],
    "on_det": [
      {
        "nombre": "LR7AO - ON Laboratorios Richmond Serie 7 Cl A Vto 10/12/26",
        "total": 322936098.0,
        "total_prev": 322691262.0,
        "cierre": 1.0765,
        "cantidad": 300000000.0
      },
      {
        "nombre": "VBC3O - ON BANCO DE VALORES CL.3 24/10/26 $",
        "total": 304927650.0,
        "total_prev": 304728609.0,
        "cierre": 1.0164,
        "cantidad": 300000000.0
      }
    ],
    "ff_det": [
      {
        "nombre": "FF AMFAyS S49 Clase A",
        "total": 40646088.0,
        "total_prev": 40619635.0,
        "cierre": 0.4065,
        "cantidad": 100000000.0
      },
      {
        "nombre": "MY50B - VD FF AMFAYS S.50 CL.B $",
        "total": 134673115.84,
        "total_prev": 134630166.37,
        "cierre": 1.3208,
        "cantidad": 101962042.0
      },
      {
        "nombre": "MY50C - VD FF AMFAYS S.50 CL.C $",
        "total": 416649145.64,
        "total_prev": 417126232.41,
        "cierre": 1.0897,
        "cantidad": 382357659.0
      },
      {
        "nombre": "MY51B - VD FF AMFAYS Serie 51 Clase B",
        "total": 79696025.93,
        "total_prev": 79759856.8,
        "cierre": 1.0544,
        "cantidad": 75584213.0
      },
      {
        "nombre": "MY51C - VD FF AMFAYS Serie 51 Clase C",
        "total": 170140922.46,
        "total_prev": 170152144.45,
        "cierre": 0.9647,
        "cantidad": 176363163.0
      },
      {
        "nombre": "VD FF SECUBONO 245 CL.A $",
        "total": 136857247.17,
        "total_prev": 136754865.56,
        "cierre": 0.4468,
        "cantidad": 306275000.0
      }
    ],
    "prov_det": [
      {
        "nombre": "CO2D7 - Título provincia de Córdoba 05/12/27",
        "total": 306461808.0,
        "total_prev": 307758267.0,
        "cierre": 1.0215,
        "cantidad": 300000000.0
      }
    ],
    "money_market_det": [
      {
        "nombre": "FCI IEB Ahorro - Clase E",
        "total": 1680000000.0,
        "total_prev": null,
        "cierre": 12.1888
      }
    ]
  },
  "futuros": [
    {
      "contrato": "Fut Rofex DLR052026",
      "cantidad": -40000.0,
      "cierre": 1406.5,
      "total_hoy": -56260000.0,
      "total_prev": null
    },
    {
      "contrato": "Fut Rofex DLR062026",
      "cantidad": -414000.0,
      "cierre": 1432.0,
      "total_hoy": -592848000.0,
      "total_prev": null
    },
    {
      "contrato": "Fut Rofex DLR072026",
      "cantidad": -301000.0,
      "cierre": 1460.5,
      "total_hoy": -439610500.0,
      "total_prev": null
    },
    {
      "contrato": "Fut Rofex DLR082026",
      "cantidad": -125000.0,
      "cierre": 1490.5,
      "total_hoy": -186312500.0,
      "total_prev": null
    },
    {
      "contrato": "Fut Rofex DLR092026",
      "cantidad": -75000.0,
      "cierre": 1521.5,
      "total_hoy": -114112500.0,
      "total_prev": null
    }
  ],
  "cuotapartes": {
    "A": {
      "vcp": 1382.404,
      "vcp_prev": 1382.404,
      "vcp_abril": null,
      "vcp_dic": null,
      "saldo_cp": 3682051634,
      "inversion": 5045345845,
      "inversion_prev": 5045345845,
      "saldo_cp_prev": 3649689848,
      "ingresos_hoy": 114420000,
      "egresos_hoy": 69651352,
      "ingresos_prev": 10340022,
      "egresos_prev": 2029998
    },
    "B": {
      "vcp": 1656.493,
      "vcp_prev": 1656.493,
      "vcp_abril": null,
      "vcp_dic": null,
      "saldo_cp": 2907141437,
      "inversion": 4664315164,
      "inversion_prev": 4664315164,
      "saldo_cp_prev": 2815777165,
      "ingresos_hoy": 151451173,
      "egresos_hoy": 0,
      "ingresos_prev": 0,
      "egresos_prev": 0
    },
    "C": {
      "vcp": 1668.797,
      "vcp_prev": 1668.797,
      "vcp_abril": null,
      "vcp_dic": null,
      "saldo_cp": 17456821199,
      "inversion": 29131890846,
      "inversion_prev": 29131890846,
      "saldo_cp_prev": 17456821199,
      "ingresos_hoy": 0,
      "egresos_hoy": 0,
      "ingresos_prev": 800000000,
      "egresos_prev": 0
    }
  },
  "cuotapartistas_ext": [
    {
      "nombre": "ZOFINGEN SECURITIES",
      "clase": "C",
      "inversion": 557514499,
      "cuotapartes": 334081676
    },
    {
      "nombre": "BANCO DE LA CIUDAD DE BUENOS AIRES",
      "clase": "C",
      "inversion": 2328439420,
      "cuotapartes": 1395280205
    },
    {
      "nombre": "ALYCBUR",
      "clase": "C",
      "inversion": 566982390,
      "cuotapartes": 339755159
    },
    {
      "nombre": "ZOFINGEN INVESTMENT SA",
      "clase": "A",
      "inversion": 0,
      "cuotapartes": null
    },
    {
      "nombre": "ZOFINGEN SECURITIES",
      "clase": "A",
      "inversion": 0,
      "cuotapartes": null
    },
    {
      "nombre": "ALYCBUR",
      "clase": "A",
      "inversion": 619135185,
      "cuotapartes": 447868485
    },
    {
      "nombre": "BANCO DE LA CIUDAD DE BUENOS AIRES",
      "clase": "B",
      "inversion": 0,
      "cuotapartes": null
    },
    {
      "nombre": "ALYCBUR",
      "clase": "B",
      "inversion": 280180507,
      "cuotapartes": 169140773
    }
  ],
  "cpd_vencimientos": [
    {
      "fecha": "21/05",
      "dia": "Jue",
      "monto": 108004789
    },
    {
      "fecha": "22/05",
      "dia": "Vie",
      "monto": 567037950
    },
    {
      "fecha": "26/05",
      "dia": "Mar",
      "monto": 144155632
    },
    {
      "fecha": "27/05",
      "dia": "Mié",
      "monto": 242624733
    },
    {
      "fecha": "28/05",
      "dia": "Jue",
      "monto": 1006856209
    },
    {
      "fecha": "29/05",
      "dia": "Vie",
      "monto": 319506658
    },
    {
      "fecha": "01/06",
      "dia": "Lun",
      "monto": 1162925258
    },
    {
      "fecha": "02/06",
      "dia": "Mar",
      "monto": 428365363
    },
    {
      "fecha": "03/06",
      "dia": "Mié",
      "monto": 391549140
    },
    {
      "fecha": "04/06",
      "dia": "Jue",
      "monto": 121962504
    },
    {
      "fecha": "05/06",
      "dia": "Vie",
      "monto": 364956304
    },
    {
      "fecha": "08/06",
      "dia": "Lun",
      "monto": 125769792
    },
    {
      "fecha": "09/06",
      "dia": "Mar",
      "monto": 592009780
    },
    {
      "fecha": "10/06",
      "dia": "Mié",
      "monto": 1052290276
    },
    {
      "fecha": "11/06",
      "dia": "Jue",
      "monto": 871177101
    }
  ],
  "atribucion": {
    "delta_total": 7.0603,
    "pn_prev": 38841552789,
    "items": [
      {
        "n": "Resultado Títulos Públicos en $",
        "t": "Precio",
        "bps": -0.0356,
        "dp": -0.1381,
        "det": "Código 4000000000000000001"
      },
      {
        "n": "Diferencia de Cotizacion US3",
        "t": "Precio",
        "bps": 0.9634,
        "dp": 3.742,
        "det": "Código 4000000000000000009"
      },
      {
        "n": "Resultado Cheque Pago diferido US3",
        "t": "Devengo",
        "bps": 0.0695,
        "dp": 0.2699,
        "det": "Código 4000000000000000010"
      },
      {
        "n": "Resultado de Operacion Futuro",
        "t": "MTM",
        "bps": -0.1359,
        "dp": -0.528,
        "det": "Código 4000000000000000013"
      },
      {
        "n": "Gastos por negociación de Cheque de Pago Diferido",
        "t": "Costo",
        "bps": -0.1879,
        "dp": -0.7297,
        "det": "Código 4001001000000000013"
      },
      {
        "n": "Gastos por Negociacion de Cheque de Pago Diferido DMAE",
        "t": "Costo",
        "bps": -0.0089,
        "dp": -0.0344,
        "det": "Código 4001001000000000021"
      },
      {
        "n": "Resultado por CPD incobrables",
        "t": "Costo",
        "bps": -0.0,
        "dp": -0.0,
        "det": "Código 4001002000000000021"
      },
      {
        "n": "Honorarios de Administración",
        "t": "Costo",
        "bps": -0.7319,
        "dp": -2.8429,
        "det": "Código 4001002001000000000"
      },
      {
        "n": "Resultado Cheques de Pago Diferido",
        "t": "Devengo",
        "bps": 6.7623,
        "dp": 26.2659,
        "det": "Código 4002001000000000017"
      },
      {
        "n": "Intereses Pase",
        "t": "Devengo",
        "bps": 0.155,
        "dp": 0.6021,
        "det": "Código 4002001000000000022"
      },
      {
        "n": "Intereses Caución",
        "t": "Devengo",
        "bps": -0.0,
        "dp": -0.0,
        "det": "Código 4002001002000000002"
      },
      {
        "n": "Resultado por Tenencia Títulos Provinciales",
        "t": "Precio",
        "bps": -0.3338,
        "dp": -1.2965,
        "det": "Código 4002001004000000013"
      },
      {
        "n": "Gastos Soc. Depositaria",
        "t": "Costo",
        "bps": -0.0685,
        "dp": -0.2663,
        "det": "Neto: Gastos Depositaria Clase A + B + C"
      },
      {
        "n": "Money Market (FCI)",
        "t": "Devengo",
        "bps": 0.301,
        "dp": 1.1691,
        "det": "Neto: Ventas FCI − Costo FCI"
      },
      {
        "n": "Residual / ajustes contables",
        "t": "Otros",
        "bps": 0.3116,
        "dp": null,
        "det": "Diferencia entre RESULTADOS total y cuentas desagregadas"
      }
    ]
  }
}